cowin/__init__.py
cowin/api.py
cowin/constants.py
cowin/exceptions.py
cowin/utils.py
cowin_async-1.1.dist-info/LICENSE
cowin_async-1.1.dist-info/METADATA
cowin_async-1.1.dist-info/WHEEL
cowin_async-1.1.dist-info/top_level.txt
cowin_async-1.1.dist-info/RECORD
