Metadata-Version: 2.1
Name: cowin-async
Version: 1.1
Summary: Interact with CoWin APIs
Home-page: UNKNOWN
Author: Prasanna Venkadesh
Author-email: prasmailme@gmail.com
License: LGPL v3.0
Project-URL: Source, https://gitlab.com/prashere/cowin-async
Platform: UNKNOWN
Classifier: Development Status :: 4 - Beta
Classifier: Environment :: Web Environment
Classifier: Intended Audience :: Developers
Classifier: License :: OSI Approved :: GNU Lesser General Public License v3 (LGPLv3)
Classifier: Operating System :: OS Independent
Classifier: Topic :: Internet :: WWW/HTTP
Classifier: Framework :: AsyncIO
Classifier: Framework :: Trio
Classifier: Programming Language :: Python :: 3.8
Classifier: Programming Language :: Python :: 3.9
Classifier: Programming Language :: Python :: 3 :: Only
Requires-Python: >=3.8
Requires-Dist: httpx (==0.18.*)
Provides-Extra: develop
Requires-Dist: pytest-asyncio (==0.15.1) ; extra == 'develop'
Requires-Dist: pytest-cov (==2.11.1) ; extra == 'develop'
Requires-Dist: pytest-httpx (==0.12.0) ; extra == 'develop'
Requires-Dist: pytest (==6.2.4) ; extra == 'develop'
